numtoolkit/__init__.py
numtoolkit/_dev.py
numtoolkit/integration.py
numtoolkit/spectral.py
numtoolkit-0.3.0.dist-info/LICENSE
numtoolkit-0.3.0.dist-info/METADATA
numtoolkit-0.3.0.dist-info/WHEEL
numtoolkit-0.3.0.dist-info/top_level.txt
numtoolkit-0.3.0.dist-info/RECORD
